setup.py
automata_ssh.egg-info/PKG-INFO
automata_ssh.egg-info/SOURCES.txt
automata_ssh.egg-info/dependency_links.txt
automata_ssh.egg-info/entry_points.txt
automata_ssh.egg-info/not-zip-safe
automata_ssh.egg-info/requires.txt
automata_ssh.egg-info/top_level.txt
automatagl/__init__.py
automatagl/automatagl.py
automatagl/helpers/__init__.py
automatagl/helpers/config_operations.py
automatagl/helpers/github_operations.py
automatagl/helpers/gitlab_operations.py
automatagl/helpers/instance_id_object.py
automatagl/helpers/ssh_key_object.py
automatagl/helpers/user_operations.py